processpy/__init__.py
processpy/PManager.py
processpy-0.1.0.dist-info/LICENSE
processpy-0.1.0.dist-info/WHEEL
processpy-0.1.0.dist-info/METADATA
processpy-0.1.0.dist-info/RECORD
