Metadata-Version: 2.1
Name: processpy
Version: 0.1.0
Summary: Python Process or Thread Manager
Home-page: https://github.com/nazmulnnb/processpy
License: MIT
Author: Nazmul Hasan
Author-email: edufornazmul@gmail.com
Requires-Python: >=3.6,<4.0
Classifier: License :: OSI Approved :: MIT License
Classifier: Operating System :: OS Independent
Classifier: Programming Language :: Python
Classifier: Programming Language :: Python :: 3
Classifier: Programming Language :: Python :: 3 :: Only
Classifier: Programming Language :: Python :: 3.10
Classifier: Programming Language :: Python :: 3.6
Classifier: Programming Language :: Python :: 3.7
Classifier: Programming Language :: Python :: 3.8
Classifier: Programming Language :: Python :: 3.9
Project-URL: Repository, https://github.com/nazmulnnb/processpy
